classy_csv/__init__.py
classy_csv/classy_csv.py
classy_csv-0.1.2.dist-info/LICENSE
classy_csv-0.1.2.dist-info/METADATA
classy_csv-0.1.2.dist-info/WHEEL
classy_csv-0.1.2.dist-info/RECORD
