Metadata-Version: 2.1
Name: classy-csv
Version: 0.1.2
Summary: The easiest way to parse your CSV files
Home-page: https://github.com/GCBallesteros/Classy-CSV
License: MIT
Author: GCBallesteros
Author-email: dev+github@maxwellrules.com
Requires-Python: >=3.9,<4.0
Classifier: License :: OSI Approved :: MIT License
Classifier: Programming Language :: Python :: 3
Classifier: Programming Language :: Python :: 3.9
Classifier: Programming Language :: Python :: 3.10
Classifier: Programming Language :: Python :: 3.11
Classifier: Programming Language :: Python :: 3.12
Project-URL: Repository, https://github.com/GCBallesteros/Classy-CSV
